bleak_sigspec/__init__.py
bleak_sigspec/formatter.py
bleak_sigspec/utils.py
bleak_sigspec/characteristics_xml/aerobic_heart_rate_lower_limit.xml
bleak_sigspec/characteristics_xml/aerobic_heart_rate_upper_limit.xml
bleak_sigspec/characteristics_xml/aerobic_threshold.xml
bleak_sigspec/characteristics_xml/age.xml
bleak_sigspec/characteristics_xml/aggregate.xml
bleak_sigspec/characteristics_xml/alert_category_id.xml
bleak_sigspec/characteristics_xml/alert_category_id_bit_mask.xml
bleak_sigspec/characteristics_xml/alert_level.xml
bleak_sigspec/characteristics_xml/alert_notification_control_point.xml
bleak_sigspec/characteristics_xml/alert_status.xml
bleak_sigspec/characteristics_xml/altitude.xml
bleak_sigspec/characteristics_xml/anaerobic_heart_rate_lower_limit.xml
bleak_sigspec/characteristics_xml/anaerobic_heart_rate_upper_limit.xml
bleak_sigspec/characteristics_xml/anaerobic_threshold.xml
bleak_sigspec/characteristics_xml/analog.xml
bleak_sigspec/characteristics_xml/analog_output.xml
bleak_sigspec/characteristics_xml/apparent_wind_direction.xml
bleak_sigspec/characteristics_xml/apparent_wind_speed.xml
bleak_sigspec/characteristics_xml/appearance.xml
bleak_sigspec/characteristics_xml/average_current.xml
bleak_sigspec/characteristics_xml/average_voltage.xml
bleak_sigspec/characteristics_xml/barometric_pressure_trend.xml
bleak_sigspec/characteristics_xml/battery_level.xml
bleak_sigspec/characteristics_xml/battery_level_state.xml
bleak_sigspec/characteristics_xml/battery_power_state.xml
bleak_sigspec/characteristics_xml/blood_pressure_feature.xml
bleak_sigspec/characteristics_xml/blood_pressure_measurement.xml
bleak_sigspec/characteristics_xml/body_composition_feature.xml
bleak_sigspec/characteristics_xml/body_composition_measurement.xml
bleak_sigspec/characteristics_xml/body_sensor_location.xml
bleak_sigspec/characteristics_xml/bond_management_control_point.xml
bleak_sigspec/characteristics_xml/bond_management_features.xml
bleak_sigspec/characteristics_xml/boolean.xml
bleak_sigspec-0.0.4.dist-info/LICENSE
bleak_sigspec-0.0.4.dist-info/METADATA
bleak_sigspec-0.0.4.dist-info/WHEEL
bleak_sigspec-0.0.4.dist-info/top_level.txt
bleak_sigspec-0.0.4.dist-info/RECORD
