Metadata-Version: 2.1
Name: bleak_sigspec
Version: 0.0.4
Summary: Bleak SIG Bluetooth Low Energy Characteristics Specification Formatter
Home-page: http://github.com/Carglglz/bleak_sigspec
Author: Carlos Gil Gonzalez
Author-email: carlosgilglez@gmail.com
License: MIT
Platform: UNKNOWN
Classifier: Intended Audience :: Developers
Classifier: Intended Audience :: Science/Research
Classifier: Intended Audience :: Education
Classifier: License :: OSI Approved :: MIT License
Classifier: Programming Language :: Python :: 3.6
Classifier: Programming Language :: Python :: 3.7
Classifier: Programming Language :: Python :: 3.8
Classifier: Topic :: System :: Monitoring
Classifier: Topic :: Scientific/Engineering
Classifier: Topic :: Software Development :: Embedded Systems
